{
  "suggestions": [
    {
      "id": 1772849447908,
      "name": "Trevor L",
      "category": "Product",
      "text": "Show how many support tickets we are getting per week, how quickly we are closing and resolving them.",
      "votes": 1,
      "voters": [],
      "ts": "2026-03-07T02:10:47.908Z"
    },
    {
      "id": 1772849311417,
      "name": "Trevor L",
      "category": "Product",
      "text": "Integrate JIRA to see how many new features are being solve and how much new code we are pushing per week.",
      "votes": 0,
      "voters": [],
      "ts": "2026-03-07T02:08:31.417Z"
    }
  ]
}